zyte_parsers/__init__.py
zyte_parsers/aggregate_rating.py
zyte_parsers/api.py
zyte_parsers/brand.py
zyte_parsers/breadcrumbs.py
zyte_parsers/gtin.py
zyte_parsers/price.py
zyte_parsers/py.typed
zyte_parsers/review.py
zyte_parsers/star_rating.py
zyte_parsers/utils.py
zyte_parsers-0.5.1.dist-info/LICENSE
zyte_parsers-0.5.1.dist-info/METADATA
zyte_parsers-0.5.1.dist-info/WHEEL
zyte_parsers-0.5.1.dist-info/top_level.txt
zyte_parsers-0.5.1.dist-info/RECORD
