Metadata-Version: 2.1
Name: zyte-parsers
Version: 0.5.1
Summary: Parsing of data from web pages.
Author-email: Zyte Group Ltd <info@zyte.com>
License: The MIT License (MIT)
Project-URL: Source, https://github.com/zytedata/zyte-parsers
Classifier: Development Status :: 3 - Alpha
Classifier: Intended Audience :: Developers
Classifier: License :: OSI Approved :: BSD License
Classifier: Natural Language :: English
Classifier: Operating System :: OS Independent
Classifier: Programming Language :: Python :: 3
Classifier: Programming Language :: Python :: 3.8
Classifier: Programming Language :: Python :: 3.9
Classifier: Programming Language :: Python :: 3.10
Classifier: Programming Language :: Python :: 3.11
Classifier: Programming Language :: Python :: 3.12
Classifier: Programming Language :: Python :: Implementation :: CPython
Requires-Python: >=3.8
License-File: LICENSE
Requires-Dist: attrs >=21.3.0
Requires-Dist: gtin-validator >=1.0.3
Requires-Dist: html-text
Requires-Dist: lxml
Requires-Dist: parsel
Requires-Dist: price-parser >=0.3.4
Requires-Dist: python-stdnum >=1.19
Requires-Dist: six
Requires-Dist: w3lib
